persistent_sql/__init__.py
persistent_sql-0.2.2.dist-info/METADATA
persistent_sql-0.2.2.dist-info/WHEEL
persistent_sql-0.2.2.dist-info/top_level.txt
persistent_sql-0.2.2.dist-info/RECORD
