Metadata-Version: 2.4
Name: persistent_sql
Version: 0.2.2
Summary: Persistent SQLite Database using S3 on Cloud Workspaces
Author-email: Siddharth Singh <siddharthsingh5010@icloud.com>
Requires-Python: >=3.6
Requires-Dist: boto3
Requires-Dist: pandas
Requires-Dist: numpy
